kinto_redis/__init__.py
kinto_redis/cache.py
kinto_redis/listeners.py
kinto_redis/permission.py
kinto_redis/storage.py
kinto_redis/tests/__init__.py
kinto_redis/tests/test_cache.py
kinto_redis/tests/test_listeners.py
kinto_redis/tests/test_permission.py
kinto_redis/tests/test_storage.py
kinto_redis-2.0.0.dist-info/METADATA
kinto_redis-2.0.0.dist-info/WHEEL
kinto_redis-2.0.0.dist-info/top_level.txt
kinto_redis-2.0.0.dist-info/RECORD
